GirardProxy/__init__.py
GirardProxy/proxy.py
GirardProxy-1.0.0.dist-info/LICENSE
GirardProxy-1.0.0.dist-info/METADATA
GirardProxy-1.0.0.dist-info/WHEEL
GirardProxy-1.0.0.dist-info/top_level.txt
GirardProxy-1.0.0.dist-info/RECORD
