Metadata-Version: 2.1
Name: GirardProxy
Version: 1.0.0
Summary: Python module that scrape and retrive working proxy addresses
Author: Girard
Author-email: girardhappy.it@gmail.com
License: MIT
Keywords: proxy scraper
Classifier: Development Status :: 4 - Beta
Classifier: Topic :: Utilities
Classifier: License :: OSI Approved :: MIT License
License-File: LICENSE
Requires-Dist: requests[socks]
